moe_musicbrainz/__init__.py
moe_musicbrainz/mb_cli.py
moe_musicbrainz/mb_core.py
moe_musicbrainz-1.1.0.dist-info/LICENSE
moe_musicbrainz-1.1.0.dist-info/METADATA
moe_musicbrainz-1.1.0.dist-info/WHEEL
moe_musicbrainz-1.1.0.dist-info/entry_points.txt
moe_musicbrainz-1.1.0.dist-info/RECORD
