Metadata-Version: 2.3
Name: moe_musicbrainz
Version: 1.1.0
Summary: Template plugin repository.
License: MIT
Author: Jacob Pavlock
Author-email: jtpavlock@gmail.com
Requires-Python: >=3.9,<3.14
Classifier: License :: OSI Approved :: MIT License
Classifier: Programming Language :: Python :: 3
Classifier: Programming Language :: Python :: 3.9
Classifier: Programming Language :: Python :: 3.10
Classifier: Programming Language :: Python :: 3.11
Classifier: Programming Language :: Python :: 3.12
Classifier: Programming Language :: Python :: 3.13
Requires-Dist: moe (>=2.1.3,<3.0.0)
Project-URL: Documentation, https://moe-musicbrainz.readthedocs.io/en/latest/
